LICENSE
MANIFEST.in
README.md
pyproject.toml
requirements.txt
setup.py
deep_pipe.egg-info/PKG-INFO
deep_pipe.egg-info/SOURCES.txt
deep_pipe.egg-info/dependency_links.txt
deep_pipe.egg-info/entry_points.txt
deep_pipe.egg-info/requires.txt
deep_pipe.egg-info/top_level.txt
dpipe/__init__.py
dpipe/__version__.py
dpipe/checks.py
dpipe/commands.py
dpipe/io.py
dpipe/itertools.py
dpipe/py.typed
dpipe/batch_iter/__init__.py
dpipe/batch_iter/_pdp.py
dpipe/batch_iter/expiration_pool.py
dpipe/batch_iter/pipeline.py
dpipe/batch_iter/sources.py
dpipe/batch_iter/utils.py
dpipe/config/__init__.py
dpipe/config/commands_runner.py
dpipe/dataset/__init__.py
dpipe/dataset/base.py
dpipe/dataset/csv.py
dpipe/dataset/dicom.py
dpipe/dataset/segmentation.py
dpipe/dataset/wrappers.py
dpipe/im/__init__.py
dpipe/im/augmentation.py
dpipe/im/axes.py
dpipe/im/box.py
dpipe/im/dist.py
dpipe/im/grid.py
dpipe/im/hsv.py
dpipe/im/metrics.py
dpipe/im/patch.py
dpipe/im/preprocessing.py
dpipe/im/shape_ops.py
dpipe/im/shape_utils.py
dpipe/im/slices.py
dpipe/im/utils.py
dpipe/im/visualize.py
dpipe/layers/__init__.py
dpipe/layers/conv.py
dpipe/layers/fpn.py
dpipe/layers/resblock.py
dpipe/layers/shape.py
dpipe/layers/structure.py
dpipe/layout/__init__.py
dpipe/layout/base.py
dpipe/layout/scripts.py
dpipe/predict/__init__.py
dpipe/predict/functional.py
dpipe/predict/shape.py
dpipe/split/__init__.py
dpipe/split/base.py
dpipe/split/cv.py
dpipe/torch/__init__.py
dpipe/torch/functional.py
dpipe/torch/model.py
dpipe/torch/utils.py
dpipe/train/__init__.py
dpipe/train/base.py
dpipe/train/checkpoint.py
dpipe/train/logging.py
dpipe/train/policy.py
dpipe/train/validator.py
tests/test_gradient_accumulation.py
tests/test_itertools.py
tests/test_mnist.py