Metadata-Version: 2.4
Name: deep_pipe
Version: 0.5.0
Summary: A collection of tools for deep learning experiments
Home-page: https://github.com/neuro-ml/deep_pipe
Download-URL: https://github.com/neuro-ml/deep_pipe/v0.5.0.tar.gz
Author: NeuroML Group
License: MIT License
Project-URL: Homepage, https://github.com/neuro-ml/deep_pipe
Project-URL: Issues, https://github.com/neuro-ml/deep_pipe/issues
Project-URL: Source, https://github.com/neuro-ml/deep_pipe
Classifier: Development Status :: 4 - Beta
Classifier: License :: OSI Approved :: MIT License
Classifier: Programming Language :: Python :: 3
Classifier: Programming Language :: Python :: 3.7
Classifier: Programming Language :: Python :: 3.8
Classifier: Programming Language :: Python :: 3.9
Classifier: Programming Language :: Python :: 3.10
Classifier: Programming Language :: Python :: 3.11
Classifier: Programming Language :: Python :: 3.12
Classifier: Programming Language :: Python :: 3.13
Classifier: Programming Language :: Python :: 3 :: Only
Requires-Python: >=3.7
License-File: LICENSE
Requires-Dist: imageio
Requires-Dist: numpy<3.0.0
Requires-Dist: scipy
Requires-Dist: pandas
Requires-Dist: scikit-learn>=0.19
Requires-Dist: tqdm
Requires-Dist: pdp==0.3.*
Requires-Dist: lazycon<1.0.0,>=0.1.0
Requires-Dist: loky<4.0.0,>=3.0.0
Requires-Dist: torch
Requires-Dist: imops<1.0.0,>=0.8.4
Dynamic: author
Dynamic: download-url
Dynamic: home-page
Dynamic: license-file
Dynamic: requires-python
